[{"precio":58801,"producto":"Scraper"},
{"precio":37042,"producto":"Skid-Steer"},
{"precio":9175,"producto":"Grader"},
{"precio":38618,"producto":"Scraper"},
{"precio":5365,"producto":"Scraper"},
{"precio":17888,"producto":"Excavator"},
{"precio":16083,"producto":"Trencher"},
{"precio":37262,"producto":"Compactor"},
{"precio":7842,"producto":"Excavator"},
{"precio":12365,"producto":"Compactor"},
{"precio":36145,"producto":"Compactor"},
{"precio":1759,"producto":"Backhoe"},
{"precio":73555,"producto":"Scraper"},
{"precio":30151,"producto":"Grader"},
{"precio":23122,"producto":"Bulldozer"},
{"precio":4291,"producto":"Trencher"},
{"precio":70976,"producto":"Dragline"},
{"precio":34963,"producto":"Backhoe"},
{"precio":69730,"producto":"Bulldozer"},
{"precio":35988,"producto":"Dragline"},
{"precio":56242,"producto":"Compactor"},
{"precio":93175,"producto":"Crawler"},
{"precio":11724,"producto":"Crawler"},
{"precio":31478,"producto":"Excavator"},
{"precio":53919,"producto":"Backhoe"},
{"precio":68690,"producto":"Grader"},
{"precio":26877,"producto":"Skid-Steer"},
{"precio":71652,"producto":"Excavator"},
{"precio":7938,"producto":"Dragline"},
{"precio":10685,"producto":"Skid-Steer"},
{"precio":48453,"producto":"Bulldozer"},
{"precio":95455,"producto":"Excavator"},
{"precio":50630,"producto":"Crawler"},
{"precio":51690,"producto":"Grader"},
{"precio":94956,"producto":"Dragline"},
{"precio":49728,"producto":"Trencher"},
{"precio":55356,"producto":"Backhoe"},
{"precio":39146,"producto":"Crawler"},
{"precio":43278,"producto":"Skid-Steer"},
{"precio":52507,"producto":"Grader"},
{"precio":43800,"producto":"Compactor"},
{"precio":46759,"producto":"Scraper"},
{"precio":64700,"producto":"Scraper"},
{"precio":65184,"producto":"Backhoe"},
{"precio":76917,"producto":"Trencher"},
{"precio":38020,"producto":"Bulldozer"},
{"precio":8174,"producto":"Crawler"},
{"precio":48680,"producto":"Backhoe"},
{"precio":67803,"producto":"Compactor"},
{"precio":49007,"producto":"Crawler"},
{"precio":56944,"producto":"Dragline"},
{"precio":29821,"producto":"Skid-Steer"},
{"precio":95500,"producto":"Bulldozer"},
{"precio":70704,"producto":"Skid-Steer"},
{"precio":35314,"producto":"Dump Truck"},
{"precio":60008,"producto":"Excavator"},
{"precio":45774,"producto":"Backhoe"},
{"precio":19447,"producto":"Scraper"},
{"precio":69140,"producto":"Dragline"},
{"precio":77444,"producto":"Dragline"},
{"precio":54571,"producto":"Compactor"},
{"precio":84598,"producto":"Bulldozer"},
{"precio":97889,"producto":"Grader"},
{"precio":78275,"producto":"Skid-Steer"},
{"precio":55501,"producto":"Dump Truck"},
{"precio":34334,"producto":"Dump Truck"},
{"precio":6366,"producto":"Dump Truck"},
{"precio":87526,"producto":"Backhoe"},
{"precio":75844,"producto":"Bulldozer"},
{"precio":38447,"producto":"Excavator"},
{"precio":24881,"producto":"Backhoe"},
{"precio":69302,"producto":"Trencher"},
{"precio":26867,"producto":"Dump Truck"},
{"precio":63366,"producto":"Dump Truck"},
{"precio":7856,"producto":"Excavator"},
{"precio":19819,"producto":"Backhoe"},
{"precio":58277,"producto":"Trencher"},
{"precio":23078,"producto":"Dump Truck"},
{"precio":94519,"producto":"Bulldozer"},
{"precio":14896,"producto":"Excavator"},
{"precio":36444,"producto":"Scraper"},
{"precio":28344,"producto":"Dump Truck"},
{"precio":2367,"producto":"Scraper"},
{"precio":72144,"producto":"Scraper"},
{"precio":69207,"producto":"Dragline"},
{"precio":72957,"producto":"Trencher"},
{"precio":15301,"producto":"Crawler"},
{"precio":24610,"producto":"Excavator"},
{"precio":83931,"producto":"Crawler"},
{"precio":56913,"producto":"Scraper"},
{"precio":66190,"producto":"Trencher"},
{"precio":29936,"producto":"Grader"},
{"precio":60170,"producto":"Bulldozer"},
{"precio":72473,"producto":"Excavator"},
{"precio":24177,"producto":"Dragline"},
{"precio":34427,"producto":"Compactor"},
{"precio":83991,"producto":"Grader"},
{"precio":4940,"producto":"Grader"},
{"precio":93705,"producto":"Skid-Steer"},
{"precio":27978,"producto":"Bulldozer"},
{"precio":56225,"producto":"Backhoe"},
{"precio":75329,"producto":"Dragline"},
{"precio":67114,"producto":"Dragline"},
{"precio":57579,"producto":"Skid-Steer"},
{"precio":15646,"producto":"Excavator"},
{"precio":75553,"producto":"Crawler"},
{"precio":78215,"producto":"Dragline"},
{"precio":16887,"producto":"Excavator"},
{"precio":4317,"producto":"Backhoe"},
{"precio":19413,"producto":"Backhoe"},
{"precio":99008,"producto":"Scraper"},
{"precio":42363,"producto":"Dragline"},
{"precio":63527,"producto":"Compactor"},
{"precio":60770,"producto":"Dragline"},
{"precio":34029,"producto":"Trencher"},
{"precio":67584,"producto":"Bulldozer"},
{"precio":31396,"producto":"Dump Truck"},
{"precio":13416,"producto":"Backhoe"},
{"precio":28624,"producto":"Excavator"},
{"precio":5796,"producto":"Skid-Steer"},
{"precio":39393,"producto":"Skid-Steer"},
{"precio":68643,"producto":"Backhoe"},
{"precio":53095,"producto":"Grader"},
{"precio":80249,"producto":"Skid-Steer"},
{"precio":94739,"producto":"Bulldozer"},
{"precio":79913,"producto":"Dump Truck"},
{"precio":50210,"producto":"Dump Truck"},
{"precio":24704,"producto":"Skid-Steer"},
{"precio":90517,"producto":"Dump Truck"},
{"precio":81873,"producto":"Dump Truck"},
{"precio":96140,"producto":"Dragline"},
{"precio":89555,"producto":"Compactor"},
{"precio":20871,"producto":"Bulldozer"},
{"precio":7090,"producto":"Dump Truck"},
{"precio":29091,"producto":"Backhoe"},
{"precio":81364,"producto":"Grader"},
{"precio":68912,"producto":"Dump Truck"},
{"precio":71034,"producto":"Dragline"},
{"precio":8406,"producto":"Crawler"},
{"precio":1307,"producto":"Dragline"},
{"precio":21667,"producto":"Skid-Steer"},
{"precio":79700,"producto":"Dragline"},
{"precio":55166,"producto":"Skid-Steer"},
{"precio":95618,"producto":"Grader"},
{"precio":11350,"producto":"Skid-Steer"},
{"precio":60017,"producto":"Excavator"},
{"precio":97288,"producto":"Scraper"},
{"precio":60533,"producto":"Excavator"},
{"precio":8289,"producto":"Backhoe"},
{"precio":55562,"producto":"Grader"},
{"precio":74414,"producto":"Skid-Steer"},
{"precio":57193,"producto":"Grader"},
{"precio":73910,"producto":"Trencher"},
{"precio":58959,"producto":"Backhoe"},
{"precio":20641,"producto":"Dragline"},
{"precio":73400,"producto":"Dragline"},
{"precio":26146,"producto":"Dragline"},
{"precio":91024,"producto":"Backhoe"},
{"precio":26351,"producto":"Trencher"},
{"precio":21893,"producto":"Scraper"},
{"precio":46982,"producto":"Grader"},
{"precio":31522,"producto":"Grader"},
{"precio":24331,"producto":"Grader"},
{"precio":38705,"producto":"Grader"},
{"precio":79342,"producto":"Dragline"},
{"precio":85930,"producto":"Trencher"},
{"precio":5569,"producto":"Trencher"},
{"precio":49516,"producto":"Trencher"},
{"precio":93680,"producto":"Skid-Steer"},
{"precio":84678,"producto":"Dragline"},
{"precio":53363,"producto":"Grader"},
{"precio":40786,"producto":"Excavator"},
{"precio":8471,"producto":"Scraper"},
{"precio":80541,"producto":"Skid-Steer"},
{"precio":47275,"producto":"Bulldozer"},
{"precio":98847,"producto":"Skid-Steer"},
{"precio":76084,"producto":"Scraper"},
{"precio":72374,"producto":"Trencher"},
{"precio":25098,"producto":"Scraper"},
{"precio":51305,"producto":"Bulldozer"},
{"precio":39064,"producto":"Backhoe"},
{"precio":33811,"producto":"Backhoe"},
{"precio":88490,"producto":"Bulldozer"},
{"precio":65332,"producto":"Skid-Steer"},
{"precio":89107,"producto":"Trencher"},
{"precio":41064,"producto":"Dump Truck"},
{"precio":16159,"producto":"Bulldozer"},
{"precio":24061,"producto":"Crawler"},
{"precio":43364,"producto":"Grader"},
{"precio":55565,"producto":"Compactor"},
{"precio":46344,"producto":"Crawler"},
{"precio":48616,"producto":"Crawler"},
{"precio":27866,"producto":"Skid-Steer"},
{"precio":13011,"producto":"Excavator"},
{"precio":18739,"producto":"Excavator"},
{"precio":97897,"producto":"Bulldozer"},
{"precio":99172,"producto":"Backhoe"},
{"precio":28992,"producto":"Bulldozer"},
{"precio":41035,"producto":"Dump Truck"},
{"precio":65543,"producto":"Dump Truck"},
{"precio":90497,"producto":"Skid-Steer"},
{"precio":61489,"producto":"Dump Truck"},
{"precio":1145,"producto":"Dump Truck"},
{"precio":98406,"producto":"Skid-Steer"},
{"precio":2394,"producto":"Bulldozer"},
{"precio":89008,"producto":"Compactor"},
{"precio":68048,"producto":"Grader"},
{"precio":46317,"producto":"Bulldozer"},
{"precio":29350,"producto":"Compactor"},
{"precio":74104,"producto":"Crawler"},
{"precio":8243,"producto":"Compactor"},
{"precio":57439,"producto":"Dragline"},
{"precio":80415,"producto":"Trencher"},
{"precio":3949,"producto":"Crawler"},
{"precio":82186,"producto":"Backhoe"},
{"precio":66540,"producto":"Crawler"},
{"precio":88976,"producto":"Bulldozer"},
{"precio":77266,"producto":"Dump Truck"},
{"precio":24719,"producto":"Dragline"},
{"precio":53322,"producto":"Compactor"},
{"precio":45807,"producto":"Dump Truck"},
{"precio":32481,"producto":"Skid-Steer"},
{"precio":20880,"producto":"Grader"},
{"precio":45503,"producto":"Grader"},
{"precio":62422,"producto":"Backhoe"},
{"precio":55351,"producto":"Crawler"},
{"precio":14084,"producto":"Bulldozer"},
{"precio":39671,"producto":"Skid-Steer"},
{"precio":96860,"producto":"Crawler"},
{"precio":22123,"producto":"Grader"},
{"precio":77935,"producto":"Backhoe"},
{"precio":36367,"producto":"Dump Truck"},
{"precio":48798,"producto":"Excavator"},
{"precio":16449,"producto":"Backhoe"},
{"precio":88609,"producto":"Crawler"},
{"precio":59259,"producto":"Crawler"},
{"precio":25558,"producto":"Dragline"},
{"precio":55794,"producto":"Dragline"},
{"precio":86563,"producto":"Excavator"},
{"precio":20656,"producto":"Dragline"},
{"precio":78689,"producto":"Crawler"},
{"precio":71032,"producto":"Excavator"},
{"precio":44957,"producto":"Compactor"},
{"precio":52989,"producto":"Grader"},
{"precio":94035,"producto":"Trencher"},
{"precio":35845,"producto":"Scraper"},
{"precio":27772,"producto":"Excavator"},
{"precio":35272,"producto":"Dump Truck"},
{"precio":19644,"producto":"Trencher"},
{"precio":5774,"producto":"Grader"},
{"precio":14060,"producto":"Scraper"},
{"precio":90142,"producto":"Dragline"},
{"precio":96796,"producto":"Trencher"},
{"precio":38372,"producto":"Scraper"},
{"precio":53739,"producto":"Dragline"},
{"precio":31772,"producto":"Trencher"},
{"precio":82743,"producto":"Crawler"},
{"precio":15105,"producto":"Excavator"},
{"precio":13942,"producto":"Dragline"},
{"precio":14613,"producto":"Scraper"},
{"precio":84070,"producto":"Dragline"},
{"precio":21692,"producto":"Grader"},
{"precio":78814,"producto":"Grader"},
{"precio":99796,"producto":"Excavator"},
{"precio":95417,"producto":"Bulldozer"},
{"precio":3466,"producto":"Bulldozer"},
{"precio":4341,"producto":"Grader"},
{"precio":65884,"producto":"Crawler"},
{"precio":35518,"producto":"Trencher"},
{"precio":1350,"producto":"Grader"},
{"precio":81719,"producto":"Dragline"},
{"precio":91995,"producto":"Trencher"},
{"precio":95006,"producto":"Crawler"},
{"precio":33331,"producto":"Dragline"},
{"precio":89595,"producto":"Dragline"},
{"precio":74034,"producto":"Compactor"},
{"precio":16664,"producto":"Grader"},
{"precio":57971,"producto":"Trencher"},
{"precio":65602,"producto":"Dump Truck"},
{"precio":88942,"producto":"Excavator"},
{"precio":36960,"producto":"Crawler"},
{"precio":24185,"producto":"Compactor"},
{"precio":97400,"producto":"Crawler"},
{"precio":90776,"producto":"Backhoe"},
{"precio":11091,"producto":"Backhoe"},
{"precio":50467,"producto":"Skid-Steer"},
{"precio":9551,"producto":"Skid-Steer"},
{"precio":56346,"producto":"Scraper"},
{"precio":37290,"producto":"Skid-Steer"},
{"precio":6449,"producto":"Trencher"},
{"precio":30682,"producto":"Scraper"},
{"precio":33867,"producto":"Dragline"},
{"precio":92032,"producto":"Compactor"},
{"precio":97020,"producto":"Crawler"},
{"precio":93196,"producto":"Backhoe"},
{"precio":59103,"producto":"Excavator"},
{"precio":91972,"producto":"Bulldozer"},
{"precio":91449,"producto":"Trencher"},
{"precio":75447,"producto":"Crawler"},
{"precio":7327,"producto":"Grader"},
{"precio":93463,"producto":"Backhoe"},
{"precio":9786,"producto":"Crawler"},
{"precio":25657,"producto":"Bulldozer"},
{"precio":3949,"producto":"Crawler"},
{"precio":16606,"producto":"Backhoe"},
{"precio":24207,"producto":"Crawler"},
{"precio":14138,"producto":"Excavator"},
{"precio":24731,"producto":"Excavator"},
{"precio":40279,"producto":"Backhoe"},
{"precio":14722,"producto":"Dump Truck"},
{"precio":7085,"producto":"Excavator"},
{"precio":73702,"producto":"Skid-Steer"},
{"precio":3133,"producto":"Skid-Steer"},
{"precio":52079,"producto":"Trencher"},
{"precio":17959,"producto":"Excavator"},
{"precio":28654,"producto":"Trencher"},
{"precio":17717,"producto":"Skid-Steer"},
{"precio":37194,"producto":"Dump Truck"},
{"precio":72907,"producto":"Compactor"},
{"precio":2931,"producto":"Backhoe"},
{"precio":85259,"producto":"Grader"},
{"precio":76618,"producto":"Bulldozer"},
{"precio":41248,"producto":"Dragline"},
{"precio":3193,"producto":"Skid-Steer"},
{"precio":27031,"producto":"Excavator"},
{"precio":14184,"producto":"Trencher"},
{"precio":9025,"producto":"Trencher"},
{"precio":23890,"producto":"Backhoe"},
{"precio":73267,"producto":"Compactor"},
{"precio":67287,"producto":"Dump Truck"},
{"precio":41864,"producto":"Backhoe"},
{"precio":45440,"producto":"Scraper"},
{"precio":98538,"producto":"Crawler"},
{"precio":3368,"producto":"Backhoe"},
{"precio":93622,"producto":"Excavator"},
{"precio":41678,"producto":"Skid-Steer"},
{"precio":98275,"producto":"Dragline"},
{"precio":20394,"producto":"Crawler"},
{"precio":10124,"producto":"Dump Truck"},
{"precio":78349,"producto":"Compactor"},
{"precio":93027,"producto":"Excavator"},
{"precio":26370,"producto":"Excavator"},
{"precio":9334,"producto":"Dragline"},
{"precio":25879,"producto":"Excavator"},
{"precio":22058,"producto":"Dump Truck"},
{"precio":66967,"producto":"Compactor"},
{"precio":64272,"producto":"Skid-Steer"},
{"precio":13070,"producto":"Grader"},
{"precio":69307,"producto":"Excavator"},
{"precio":99820,"producto":"Bulldozer"},
{"precio":84004,"producto":"Skid-Steer"},
{"precio":80102,"producto":"Skid-Steer"},
{"precio":95610,"producto":"Excavator"},
{"precio":30796,"producto":"Skid-Steer"},
{"precio":89911,"producto":"Skid-Steer"},
{"precio":41304,"producto":"Crawler"},
{"precio":42618,"producto":"Scraper"},
{"precio":28415,"producto":"Dump Truck"},
{"precio":72077,"producto":"Excavator"},
{"precio":80125,"producto":"Trencher"},
{"precio":17728,"producto":"Grader"},
{"precio":1523,"producto":"Excavator"},
{"precio":18449,"producto":"Bulldozer"},
{"precio":14402,"producto":"Skid-Steer"},
{"precio":85031,"producto":"Compactor"},
{"precio":37780,"producto":"Excavator"},
{"precio":87111,"producto":"Crawler"},
{"precio":3820,"producto":"Skid-Steer"},
{"precio":29220,"producto":"Scraper"},
{"precio":18548,"producto":"Crawler"},
{"precio":89383,"producto":"Trencher"},
{"precio":4290,"producto":"Grader"},
{"precio":9026,"producto":"Scraper"},
{"precio":75550,"producto":"Bulldozer"},
{"precio":66683,"producto":"Compactor"},
{"precio":35999,"producto":"Compactor"},
{"precio":87464,"producto":"Dump Truck"},
{"precio":35984,"producto":"Trencher"},
{"precio":23670,"producto":"Backhoe"},
{"precio":28036,"producto":"Bulldozer"},
{"precio":30248,"producto":"Scraper"},
{"precio":59639,"producto":"Grader"},
{"precio":69948,"producto":"Grader"},
{"precio":49816,"producto":"Scraper"},
{"precio":97175,"producto":"Bulldozer"},
{"precio":2113,"producto":"Scraper"},
{"precio":82628,"producto":"Bulldozer"},
{"precio":92688,"producto":"Compactor"},
{"precio":52659,"producto":"Excavator"},
{"precio":81787,"producto":"Crawler"},
{"precio":81762,"producto":"Grader"},
{"precio":15190,"producto":"Bulldozer"},
{"precio":54677,"producto":"Dragline"},
{"precio":42301,"producto":"Trencher"},
{"precio":24054,"producto":"Compactor"},
{"precio":8161,"producto":"Dragline"},
{"precio":14529,"producto":"Dump Truck"},
{"precio":63680,"producto":"Bulldozer"},
{"precio":93655,"producto":"Scraper"},
{"precio":83386,"producto":"Compactor"},
{"precio":17330,"producto":"Excavator"},
{"precio":45256,"producto":"Crawler"},
{"precio":45401,"producto":"Dragline"},
{"precio":79071,"producto":"Crawler"},
{"precio":56885,"producto":"Crawler"},
{"precio":42178,"producto":"Dump Truck"},
{"precio":82995,"producto":"Dragline"},
{"precio":65772,"producto":"Excavator"},
{"precio":96368,"producto":"Dragline"},
{"precio":9273,"producto":"Skid-Steer"},
{"precio":61488,"producto":"Grader"},
{"precio":9033,"producto":"Dragline"},
{"precio":22619,"producto":"Compactor"},
{"precio":46800,"producto":"Excavator"},
{"precio":47655,"producto":"Backhoe"},
{"precio":41723,"producto":"Trencher"},
{"precio":84194,"producto":"Crawler"},
{"precio":61623,"producto":"Grader"},
{"precio":47309,"producto":"Backhoe"},
{"precio":99806,"producto":"Backhoe"},
{"precio":88112,"producto":"Bulldozer"},
{"precio":86621,"producto":"Scraper"},
{"precio":81040,"producto":"Crawler"},
{"precio":54529,"producto":"Dump Truck"},
{"precio":65942,"producto":"Dragline"},
{"precio":46047,"producto":"Bulldozer"},
{"precio":30138,"producto":"Backhoe"},
{"precio":8059,"producto":"Dragline"},
{"precio":17705,"producto":"Excavator"},
{"precio":18924,"producto":"Compactor"},
{"precio":80915,"producto":"Excavator"},
{"precio":62370,"producto":"Dump Truck"},
{"precio":17275,"producto":"Dragline"},
{"precio":12506,"producto":"Excavator"},
{"precio":31884,"producto":"Scraper"},
{"precio":84330,"producto":"Backhoe"},
{"precio":27444,"producto":"Scraper"},
{"precio":9065,"producto":"Trencher"},
{"precio":12184,"producto":"Trencher"},
{"precio":92390,"producto":"Dragline"},
{"precio":37732,"producto":"Crawler"},
{"precio":67961,"producto":"Trencher"},
{"precio":16357,"producto":"Crawler"},
{"precio":77593,"producto":"Bulldozer"},
{"precio":4634,"producto":"Grader"},
{"precio":86615,"producto":"Dump Truck"},
{"precio":76232,"producto":"Trencher"},
{"precio":33969,"producto":"Excavator"},
{"precio":76468,"producto":"Excavator"},
{"precio":10372,"producto":"Scraper"},
{"precio":32412,"producto":"Excavator"},
{"precio":71265,"producto":"Dump Truck"},
{"precio":35938,"producto":"Skid-Steer"},
{"precio":81196,"producto":"Grader"},
{"precio":80130,"producto":"Crawler"},
{"precio":49474,"producto":"Compactor"},
{"precio":97894,"producto":"Trencher"},
{"precio":41251,"producto":"Excavator"},
{"precio":92918,"producto":"Backhoe"},
{"precio":35410,"producto":"Skid-Steer"},
{"precio":68497,"producto":"Dump Truck"},
{"precio":88348,"producto":"Dump Truck"},
{"precio":89222,"producto":"Compactor"},
{"precio":4568,"producto":"Excavator"},
{"precio":66842,"producto":"Excavator"},
{"precio":27220,"producto":"Grader"},
{"precio":53161,"producto":"Dump Truck"},
{"precio":13454,"producto":"Compactor"},
{"precio":70027,"producto":"Dump Truck"},
{"precio":23486,"producto":"Dump Truck"},
{"precio":39846,"producto":"Excavator"},
{"precio":74746,"producto":"Skid-Steer"},
{"precio":9294,"producto":"Compactor"},
{"precio":14324,"producto":"Bulldozer"},
{"precio":30930,"producto":"Scraper"},
{"precio":90454,"producto":"Compactor"},
{"precio":46077,"producto":"Crawler"},
{"precio":2454,"producto":"Bulldozer"},
{"precio":47886,"producto":"Trencher"},
{"precio":2709,"producto":"Bulldozer"},
{"precio":38922,"producto":"Dump Truck"},
{"precio":14527,"producto":"Trencher"},
{"precio":37793,"producto":"Trencher"},
{"precio":36496,"producto":"Dragline"},
{"precio":32543,"producto":"Excavator"},
{"precio":84186,"producto":"Dragline"},
{"precio":22885,"producto":"Excavator"},
{"precio":5578,"producto":"Dump Truck"},
{"precio":62096,"producto":"Bulldozer"},
{"precio":74102,"producto":"Bulldozer"},
{"precio":48678,"producto":"Backhoe"},
{"precio":56912,"producto":"Excavator"},
{"precio":9244,"producto":"Dragline"},
{"precio":75626,"producto":"Trencher"},
{"precio":10162,"producto":"Grader"},
{"precio":79958,"producto":"Grader"},
{"precio":21678,"producto":"Grader"},
{"precio":28402,"producto":"Dump Truck"},
{"precio":64188,"producto":"Excavator"},
{"precio":38259,"producto":"Backhoe"},
{"precio":71054,"producto":"Dump Truck"},
{"precio":95870,"producto":"Grader"},
{"precio":29681,"producto":"Scraper"},
{"precio":97433,"producto":"Crawler"},
{"precio":33414,"producto":"Scraper"},
{"precio":89306,"producto":"Backhoe"},
{"precio":79767,"producto":"Scraper"},
{"precio":64976,"producto":"Grader"},
{"precio":67336,"producto":"Compactor"},
{"precio":10709,"producto":"Dragline"},
{"precio":67386,"producto":"Crawler"},
{"precio":66095,"producto":"Backhoe"},
{"precio":7498,"producto":"Backhoe"},
{"precio":9061,"producto":"Grader"},
{"precio":85766,"producto":"Bulldozer"},
{"precio":48958,"producto":"Excavator"},
{"precio":83661,"producto":"Grader"},
{"precio":16395,"producto":"Crawler"},
{"precio":41455,"producto":"Skid-Steer"},
{"precio":35621,"producto":"Grader"},
{"precio":52178,"producto":"Scraper"},
{"precio":98445,"producto":"Skid-Steer"},
{"precio":36272,"producto":"Dump Truck"},
{"precio":5623,"producto":"Backhoe"},
{"precio":60322,"producto":"Compactor"},
{"precio":97957,"producto":"Grader"},
{"precio":55455,"producto":"Dump Truck"},
{"precio":14414,"producto":"Dragline"},
{"precio":83765,"producto":"Compactor"},
{"precio":68115,"producto":"Backhoe"},
{"precio":35934,"producto":"Skid-Steer"},
{"precio":43597,"producto":"Trencher"},
{"precio":35417,"producto":"Bulldozer"},
{"precio":78350,"producto":"Bulldozer"},
{"precio":44886,"producto":"Excavator"},
{"precio":28878,"producto":"Grader"},
{"precio":16658,"producto":"Trencher"},
{"precio":17422,"producto":"Scraper"},
{"precio":76995,"producto":"Crawler"},
{"precio":12192,"producto":"Backhoe"},
{"precio":84248,"producto":"Crawler"},
{"precio":68450,"producto":"Dump Truck"},
{"precio":32890,"producto":"Excavator"},
{"precio":12778,"producto":"Scraper"},
{"precio":18025,"producto":"Grader"},
{"precio":6255,"producto":"Grader"},
{"precio":68898,"producto":"Dump Truck"},
{"precio":63444,"producto":"Scraper"},
{"precio":18432,"producto":"Crawler"},
{"precio":54949,"producto":"Grader"},
{"precio":72433,"producto":"Scraper"},
{"precio":41389,"producto":"Skid-Steer"},
{"precio":22265,"producto":"Excavator"},
{"precio":53611,"producto":"Grader"},
{"precio":58415,"producto":"Dragline"},
{"precio":13842,"producto":"Dump Truck"},
{"precio":17443,"producto":"Trencher"},
{"precio":3805,"producto":"Crawler"},
{"precio":51660,"producto":"Excavator"},
{"precio":62223,"producto":"Trencher"},
{"precio":62824,"producto":"Grader"},
{"precio":76003,"producto":"Bulldozer"},
{"precio":5484,"producto":"Compactor"},
{"precio":36372,"producto":"Dump Truck"},
{"precio":20110,"producto":"Grader"},
{"precio":14224,"producto":"Backhoe"},
{"precio":99970,"producto":"Compactor"},
{"precio":18033,"producto":"Bulldozer"},
{"precio":30626,"producto":"Trencher"},
{"precio":69146,"producto":"Compactor"},
{"precio":6458,"producto":"Dump Truck"},
{"precio":64634,"producto":"Grader"},
{"precio":4021,"producto":"Scraper"},
{"precio":39132,"producto":"Dump Truck"},
{"precio":90958,"producto":"Trencher"},
{"precio":90145,"producto":"Dump Truck"},
{"precio":79267,"producto":"Trencher"},
{"precio":96711,"producto":"Excavator"},
{"precio":89972,"producto":"Grader"},
{"precio":12372,"producto":"Trencher"},
{"precio":80598,"producto":"Dump Truck"},
{"precio":85774,"producto":"Compactor"},
{"precio":82826,"producto":"Trencher"},
{"precio":72214,"producto":"Crawler"},
{"precio":45156,"producto":"Bulldozer"},
{"precio":91846,"producto":"Crawler"},
{"precio":49784,"producto":"Excavator"},
{"precio":50832,"producto":"Grader"},
{"precio":94722,"producto":"Skid-Steer"},
{"precio":31553,"producto":"Dump Truck"},
{"precio":19409,"producto":"Compactor"},
{"precio":72961,"producto":"Trencher"},
{"precio":71959,"producto":"Skid-Steer"},
{"precio":12060,"producto":"Crawler"},
{"precio":13264,"producto":"Trencher"},
{"precio":24360,"producto":"Grader"},
{"precio":15194,"producto":"Scraper"},
{"precio":64576,"producto":"Backhoe"},
{"precio":97285,"producto":"Bulldozer"},
{"precio":91671,"producto":"Bulldozer"},
{"precio":11818,"producto":"Compactor"},
{"precio":82712,"producto":"Skid-Steer"},
{"precio":40622,"producto":"Scraper"},
{"precio":13228,"producto":"Skid-Steer"},
{"precio":66851,"producto":"Dragline"},
{"precio":20964,"producto":"Dump Truck"},
{"precio":67900,"producto":"Excavator"},
{"precio":11435,"producto":"Skid-Steer"},
{"precio":28971,"producto":"Skid-Steer"},
{"precio":79711,"producto":"Skid-Steer"},
{"precio":88582,"producto":"Backhoe"},
{"precio":44244,"producto":"Scraper"},
{"precio":34732,"producto":"Dragline"},
{"precio":11790,"producto":"Bulldozer"},
{"precio":36253,"producto":"Backhoe"},
{"precio":16970,"producto":"Crawler"},
{"precio":8595,"producto":"Bulldozer"},
{"precio":90620,"producto":"Excavator"},
{"precio":57570,"producto":"Bulldozer"},
{"precio":55727,"producto":"Crawler"},
{"precio":85962,"producto":"Bulldozer"},
{"precio":41570,"producto":"Trencher"},
{"precio":67980,"producto":"Dragline"},
{"precio":68533,"producto":"Dump Truck"},
{"precio":58366,"producto":"Grader"},
{"precio":58396,"producto":"Dragline"},
{"precio":36756,"producto":"Scraper"},
{"precio":82640,"producto":"Skid-Steer"},
{"precio":5814,"producto":"Scraper"},
{"precio":6007,"producto":"Excavator"},
{"precio":67109,"producto":"Dump Truck"},
{"precio":21257,"producto":"Skid-Steer"},
{"precio":18647,"producto":"Dump Truck"},
{"precio":33844,"producto":"Trencher"},
{"precio":84729,"producto":"Scraper"},
{"precio":6070,"producto":"Crawler"},
{"precio":16996,"producto":"Bulldozer"},
{"precio":91149,"producto":"Dump Truck"},
{"precio":39854,"producto":"Scraper"},
{"precio":31516,"producto":"Crawler"},
{"precio":52931,"producto":"Excavator"},
{"precio":40641,"producto":"Skid-Steer"},
{"precio":94629,"producto":"Grader"},
{"precio":44872,"producto":"Grader"},
{"precio":26651,"producto":"Compactor"},
{"precio":45221,"producto":"Skid-Steer"},
{"precio":87103,"producto":"Compactor"},
{"precio":63338,"producto":"Crawler"},
{"precio":99578,"producto":"Dragline"},
{"precio":7271,"producto":"Crawler"},
{"precio":97560,"producto":"Skid-Steer"},
{"precio":6271,"producto":"Excavator"},
{"precio":69783,"producto":"Excavator"},
{"precio":92382,"producto":"Bulldozer"},
{"precio":5465,"producto":"Scraper"},
{"precio":70425,"producto":"Backhoe"},
{"precio":89830,"producto":"Crawler"},
{"precio":71452,"producto":"Compactor"},
{"precio":98447,"producto":"Excavator"},
{"precio":4160,"producto":"Backhoe"},
{"precio":91040,"producto":"Backhoe"},
{"precio":59406,"producto":"Bulldozer"},
{"precio":59618,"producto":"Dump Truck"},
{"precio":79210,"producto":"Compactor"},
{"precio":92629,"producto":"Backhoe"},
{"precio":40939,"producto":"Scraper"},
{"precio":33892,"producto":"Crawler"},
{"precio":67024,"producto":"Backhoe"},
{"precio":7645,"producto":"Dragline"},
{"precio":29666,"producto":"Crawler"},
{"precio":34230,"producto":"Scraper"},
{"precio":32187,"producto":"Grader"},
{"precio":53029,"producto":"Dragline"},
{"precio":55239,"producto":"Backhoe"},
{"precio":96658,"producto":"Grader"},
{"precio":54346,"producto":"Excavator"},
{"precio":77092,"producto":"Grader"},
{"precio":47063,"producto":"Trencher"},
{"precio":2788,"producto":"Scraper"},
{"precio":22096,"producto":"Compactor"},
{"precio":23865,"producto":"Bulldozer"},
{"precio":69762,"producto":"Dragline"},
{"precio":82403,"producto":"Compactor"},
{"precio":84128,"producto":"Skid-Steer"},
{"precio":42710,"producto":"Trencher"},
{"precio":76586,"producto":"Skid-Steer"},
{"precio":45167,"producto":"Skid-Steer"},
{"precio":67215,"producto":"Compactor"},
{"precio":98772,"producto":"Bulldozer"},
{"precio":53658,"producto":"Bulldozer"},
{"precio":26823,"producto":"Grader"},
{"precio":82916,"producto":"Trencher"},
{"precio":61493,"producto":"Skid-Steer"},
{"precio":19340,"producto":"Crawler"},
{"precio":42654,"producto":"Excavator"},
{"precio":6261,"producto":"Crawler"},
{"precio":45494,"producto":"Dump Truck"},
{"precio":48790,"producto":"Compactor"},
{"precio":84216,"producto":"Grader"},
{"precio":97141,"producto":"Grader"},
{"precio":33618,"producto":"Dump Truck"},
{"precio":54801,"producto":"Trencher"},
{"precio":12145,"producto":"Excavator"},
{"precio":15053,"producto":"Dump Truck"},
{"precio":94958,"producto":"Trencher"},
{"precio":91087,"producto":"Backhoe"},
{"precio":99633,"producto":"Backhoe"},
{"precio":67221,"producto":"Crawler"},
{"precio":71882,"producto":"Grader"},
{"precio":10254,"producto":"Scraper"},
{"precio":55315,"producto":"Bulldozer"},
{"precio":89595,"producto":"Dragline"},
{"precio":43395,"producto":"Skid-Steer"},
{"precio":31931,"producto":"Grader"},
{"precio":43542,"producto":"Scraper"},
{"precio":31409,"producto":"Backhoe"},
{"precio":81663,"producto":"Backhoe"},
{"precio":43171,"producto":"Crawler"},
{"precio":38110,"producto":"Trencher"},
{"precio":46519,"producto":"Excavator"},
{"precio":25212,"producto":"Excavator"},
{"precio":50918,"producto":"Bulldozer"},
{"precio":6613,"producto":"Trencher"},
{"precio":25567,"producto":"Backhoe"},
{"precio":65657,"producto":"Bulldozer"},
{"precio":29808,"producto":"Scraper"},
{"precio":95798,"producto":"Scraper"},
{"precio":11914,"producto":"Bulldozer"},
{"precio":77040,"producto":"Backhoe"},
{"precio":71412,"producto":"Crawler"},
{"precio":56216,"producto":"Crawler"},
{"precio":64335,"producto":"Dump Truck"},
{"precio":43577,"producto":"Compactor"},
{"precio":67734,"producto":"Compactor"},
{"precio":44759,"producto":"Skid-Steer"},
{"precio":71691,"producto":"Scraper"},
{"precio":77495,"producto":"Bulldozer"},
{"precio":37644,"producto":"Dragline"},
{"precio":93427,"producto":"Excavator"},
{"precio":80224,"producto":"Scraper"},
{"precio":81330,"producto":"Excavator"},
{"precio":30157,"producto":"Compactor"},
{"precio":46707,"producto":"Excavator"},
{"precio":73601,"producto":"Trencher"},
{"precio":45253,"producto":"Crawler"},
{"precio":52108,"producto":"Skid-Steer"},
{"precio":9486,"producto":"Crawler"},
{"precio":65039,"producto":"Crawler"},
{"precio":33840,"producto":"Dragline"},
{"precio":67232,"producto":"Dump Truck"},
{"precio":77469,"producto":"Trencher"},
{"precio":43926,"producto":"Grader"},
{"precio":3350,"producto":"Crawler"},
{"precio":62024,"producto":"Bulldozer"},
{"precio":55855,"producto":"Trencher"},
{"precio":38768,"producto":"Skid-Steer"},
{"precio":35798,"producto":"Grader"},
{"precio":68143,"producto":"Crawler"},
{"precio":30430,"producto":"Dragline"},
{"precio":60412,"producto":"Bulldozer"},
{"precio":30979,"producto":"Dragline"},
{"precio":18041,"producto":"Backhoe"},
{"precio":17347,"producto":"Dump Truck"},
{"precio":86374,"producto":"Compactor"},
{"precio":9105,"producto":"Trencher"},
{"precio":34869,"producto":"Compactor"},
{"precio":65709,"producto":"Excavator"},
{"precio":47660,"producto":"Trencher"},
{"precio":11684,"producto":"Dragline"},
{"precio":77381,"producto":"Skid-Steer"},
{"precio":32564,"producto":"Trencher"},
{"precio":48699,"producto":"Grader"},
{"precio":32783,"producto":"Dump Truck"},
{"precio":10050,"producto":"Backhoe"},
{"precio":29730,"producto":"Skid-Steer"},
{"precio":35709,"producto":"Trencher"},
{"precio":71919,"producto":"Trencher"},
{"precio":24902,"producto":"Trencher"},
{"precio":27797,"producto":"Grader"},
{"precio":36437,"producto":"Dragline"},
{"precio":49712,"producto":"Dragline"},
{"precio":20543,"producto":"Dragline"},
{"precio":16168,"producto":"Dump Truck"},
{"precio":14231,"producto":"Trencher"},
{"precio":78886,"producto":"Grader"},
{"precio":74134,"producto":"Dump Truck"},
{"precio":48932,"producto":"Compactor"},
{"precio":46043,"producto":"Grader"},
{"precio":69652,"producto":"Scraper"},
{"precio":67881,"producto":"Bulldozer"},
{"precio":4843,"producto":"Grader"},
{"precio":68075,"producto":"Dump Truck"},
{"precio":80636,"producto":"Excavator"},
{"precio":82908,"producto":"Excavator"},
{"precio":74316,"producto":"Backhoe"},
{"precio":48519,"producto":"Crawler"},
{"precio":69222,"producto":"Grader"},
{"precio":61867,"producto":"Compactor"},
{"precio":49794,"producto":"Dragline"},
{"precio":75044,"producto":"Skid-Steer"},
{"precio":42726,"producto":"Scraper"},
{"precio":66692,"producto":"Crawler"},
{"precio":40444,"producto":"Crawler"},
{"precio":42612,"producto":"Compactor"},
{"precio":98720,"producto":"Skid-Steer"},
{"precio":11552,"producto":"Compactor"},
{"precio":45880,"producto":"Compactor"},
{"precio":55409,"producto":"Dump Truck"},
{"precio":42728,"producto":"Dragline"},
{"precio":89410,"producto":"Scraper"},
{"precio":45395,"producto":"Crawler"},
{"precio":38760,"producto":"Skid-Steer"},
{"precio":26480,"producto":"Scraper"},
{"precio":85943,"producto":"Compactor"},
{"precio":26471,"producto":"Grader"},
{"precio":71551,"producto":"Excavator"},
{"precio":16868,"producto":"Excavator"},
{"precio":87756,"producto":"Backhoe"},
{"precio":84257,"producto":"Trencher"},
{"precio":63385,"producto":"Grader"},
{"precio":80300,"producto":"Backhoe"},
{"precio":90147,"producto":"Grader"},
{"precio":77670,"producto":"Skid-Steer"},
{"precio":41888,"producto":"Grader"},
{"precio":11668,"producto":"Trencher"},
{"precio":18153,"producto":"Excavator"},
{"precio":17831,"producto":"Backhoe"},
{"precio":57545,"producto":"Excavator"},
{"precio":5038,"producto":"Excavator"},
{"precio":35501,"producto":"Excavator"},
{"precio":96077,"producto":"Dragline"},
{"precio":52488,"producto":"Backhoe"},
{"precio":56923,"producto":"Compactor"},
{"precio":1536,"producto":"Compactor"},
{"precio":86910,"producto":"Dump Truck"},
{"precio":62650,"producto":"Compactor"},
{"precio":43025,"producto":"Grader"},
{"precio":35788,"producto":"Crawler"},
{"precio":12680,"producto":"Bulldozer"},
{"precio":45597,"producto":"Scraper"},
{"precio":90359,"producto":"Scraper"},
{"precio":54615,"producto":"Crawler"},
{"precio":29829,"producto":"Bulldozer"},
{"precio":8336,"producto":"Excavator"},
{"precio":47305,"producto":"Compactor"},
{"precio":26095,"producto":"Scraper"},
{"precio":82267,"producto":"Dump Truck"},
{"precio":38415,"producto":"Dump Truck"},
{"precio":92140,"producto":"Dump Truck"},
{"precio":69818,"producto":"Scraper"},
{"precio":96321,"producto":"Dump Truck"},
{"precio":34250,"producto":"Dragline"},
{"precio":35245,"producto":"Grader"},
{"precio":66833,"producto":"Backhoe"},
{"precio":68555,"producto":"Crawler"},
{"precio":93428,"producto":"Backhoe"},
{"precio":72281,"producto":"Compactor"},
{"precio":5538,"producto":"Compactor"},
{"precio":4835,"producto":"Crawler"},
{"precio":7674,"producto":"Dragline"},
{"precio":11482,"producto":"Grader"},
{"precio":63820,"producto":"Grader"},
{"precio":76725,"producto":"Scraper"},
{"precio":14862,"producto":"Scraper"},
{"precio":24246,"producto":"Grader"},
{"precio":87716,"producto":"Dump Truck"},
{"precio":28887,"producto":"Dragline"},
{"precio":11569,"producto":"Scraper"},
{"precio":53833,"producto":"Excavator"},
{"precio":27216,"producto":"Scraper"},
{"precio":37369,"producto":"Grader"},
{"precio":75921,"producto":"Scraper"},
{"precio":11548,"producto":"Skid-Steer"},
{"precio":32541,"producto":"Trencher"},
{"precio":1665,"producto":"Dump Truck"},
{"precio":12065,"producto":"Trencher"},
{"precio":86506,"producto":"Bulldozer"},
{"precio":76693,"producto":"Dump Truck"},
{"precio":99825,"producto":"Compactor"},
{"precio":9528,"producto":"Scraper"},
{"precio":27718,"producto":"Skid-Steer"},
{"precio":50404,"producto":"Dump Truck"},
{"precio":47006,"producto":"Excavator"},
{"precio":74847,"producto":"Crawler"},
{"precio":8679,"producto":"Skid-Steer"},
{"precio":81724,"producto":"Trencher"},
{"precio":92854,"producto":"Grader"},
{"precio":92991,"producto":"Bulldozer"},
{"precio":68857,"producto":"Scraper"},
{"precio":60907,"producto":"Scraper"},
{"precio":86248,"producto":"Scraper"},
{"precio":83704,"producto":"Scraper"},
{"precio":42450,"producto":"Trencher"},
{"precio":2497,"producto":"Excavator"},
{"precio":6870,"producto":"Grader"},
{"precio":49223,"producto":"Scraper"},
{"precio":14811,"producto":"Scraper"},
{"precio":65716,"producto":"Crawler"},
{"precio":27525,"producto":"Skid-Steer"},
{"precio":24622,"producto":"Dragline"},
{"precio":13168,"producto":"Backhoe"},
{"precio":99915,"producto":"Bulldozer"},
{"precio":2027,"producto":"Compactor"},
{"precio":27700,"producto":"Excavator"},
{"precio":43867,"producto":"Grader"},
{"precio":78609,"producto":"Grader"},
{"precio":42265,"producto":"Compactor"},
{"precio":99670,"producto":"Compactor"},
{"precio":27130,"producto":"Excavator"},
{"precio":2034,"producto":"Trencher"},
{"precio":9230,"producto":"Crawler"},
{"precio":25999,"producto":"Crawler"},
{"precio":59933,"producto":"Crawler"},
{"precio":67944,"producto":"Skid-Steer"},
{"precio":22529,"producto":"Dump Truck"},
{"precio":91228,"producto":"Compactor"},
{"precio":77748,"producto":"Bulldozer"},
{"precio":97597,"producto":"Trencher"},
{"precio":30653,"producto":"Dragline"},
{"precio":37212,"producto":"Crawler"},
{"precio":44487,"producto":"Scraper"},
{"precio":39028,"producto":"Compactor"},
{"precio":26948,"producto":"Bulldozer"},
{"precio":93590,"producto":"Trencher"},
{"precio":26253,"producto":"Grader"},
{"precio":52109,"producto":"Excavator"},
{"precio":47344,"producto":"Dragline"},
{"precio":23102,"producto":"Trencher"},
{"precio":43508,"producto":"Crawler"},
{"precio":23779,"producto":"Grader"},
{"precio":27567,"producto":"Compactor"},
{"precio":6207,"producto":"Dump Truck"},
{"precio":7490,"producto":"Crawler"},
{"precio":23655,"producto":"Grader"},
{"precio":69532,"producto":"Excavator"},
{"precio":48432,"producto":"Scraper"},
{"precio":34034,"producto":"Crawler"},
{"precio":54053,"producto":"Dragline"},
{"precio":21224,"producto":"Grader"},
{"precio":63471,"producto":"Crawler"},
{"precio":21848,"producto":"Trencher"},
{"precio":74030,"producto":"Crawler"},
{"precio":19826,"producto":"Crawler"},
{"precio":71370,"producto":"Dragline"},
{"precio":80641,"producto":"Bulldozer"},
{"precio":23799,"producto":"Trencher"},
{"precio":20143,"producto":"Grader"},
{"precio":48584,"producto":"Crawler"},
{"precio":52814,"producto":"Bulldozer"},
{"precio":96332,"producto":"Scraper"},
{"precio":69313,"producto":"Excavator"},
{"precio":99080,"producto":"Backhoe"},
{"precio":49012,"producto":"Trencher"},
{"precio":50512,"producto":"Bulldozer"},
{"precio":23151,"producto":"Dump Truck"},
{"precio":73654,"producto":"Excavator"},
{"precio":62683,"producto":"Scraper"},
{"precio":86731,"producto":"Grader"},
{"precio":97250,"producto":"Scraper"},
{"precio":71745,"producto":"Bulldozer"},
{"precio":48630,"producto":"Excavator"},
{"precio":37200,"producto":"Dragline"},
{"precio":7967,"producto":"Compactor"},
{"precio":99425,"producto":"Scraper"},
{"precio":29423,"producto":"Skid-Steer"},
{"precio":71086,"producto":"Backhoe"},
{"precio":38331,"producto":"Backhoe"},
{"precio":3513,"producto":"Dragline"},
{"precio":51798,"producto":"Excavator"},
{"precio":71055,"producto":"Dump Truck"},
{"precio":98471,"producto":"Compactor"},
{"precio":91062,"producto":"Skid-Steer"},
{"precio":71020,"producto":"Dragline"},
{"precio":54495,"producto":"Skid-Steer"},
{"precio":29910,"producto":"Backhoe"},
{"precio":72104,"producto":"Scraper"},
{"precio":56506,"producto":"Crawler"},
{"precio":58714,"producto":"Trencher"},
{"precio":96038,"producto":"Compactor"},
{"precio":31860,"producto":"Backhoe"},
{"precio":2559,"producto":"Excavator"},
{"precio":46974,"producto":"Scraper"},
{"precio":67748,"producto":"Compactor"},
{"precio":17389,"producto":"Backhoe"},
{"precio":20556,"producto":"Grader"},
{"precio":20761,"producto":"Crawler"},
{"precio":33620,"producto":"Trencher"},
{"precio":68272,"producto":"Trencher"},
{"precio":74846,"producto":"Bulldozer"},
{"precio":94427,"producto":"Scraper"},
{"precio":72197,"producto":"Compactor"},
{"precio":5910,"producto":"Bulldozer"},
{"precio":22907,"producto":"Backhoe"},
{"precio":12660,"producto":"Excavator"},
{"precio":33181,"producto":"Dump Truck"},
{"precio":39257,"producto":"Skid-Steer"},
{"precio":99606,"producto":"Skid-Steer"},
{"precio":17128,"producto":"Skid-Steer"},
{"precio":68328,"producto":"Bulldozer"},
{"precio":13261,"producto":"Bulldozer"}]